auto_dlp/YoutubeDataAPIv3.py
auto_dlp/__init__.py
auto_dlp/__main__.py
auto_dlp/adb.py
auto_dlp/adb_fs.py
auto_dlp/adb_fs_cleaning.py
auto_dlp/age_hints.py
auto_dlp/channels.py
auto_dlp/codecs.py
auto_dlp/config_intepreter.py
auto_dlp/download_manager.py
auto_dlp/downloader.py
auto_dlp/example_file.py
auto_dlp/ffmpeg.py
auto_dlp/file_cleaning.py
auto_dlp/file_locations.py
auto_dlp/fs_sync.py
auto_dlp/image_metadata.py
auto_dlp/metadata.py
auto_dlp/name_cleaning.py
auto_dlp/playlist_items.py
auto_dlp/redownloading.py
auto_dlp/terminal_formatting.py
auto_dlp/thumbnails.py
auto_dlp/unavailable_items.py
auto_dlp/utils.py
auto_dlp/variables.py
auto_dlp/version.py
auto_dlp-2025.11.2.dist-info/METADATA
auto_dlp-2025.11.2.dist-info/WHEEL
auto_dlp-2025.11.2.dist-info/entry_points.txt
auto_dlp-2025.11.2.dist-info/licenses/LICENSE.txt
auto_dlp-2025.11.2.dist-info/RECORD
