Metadata-Version: 2.4
Name: Auto-DLP
Version: 2025.11.2
Summary: A simple and lightweight system for downloading and managing youtube playlists and songs (based on yt-dlp)
Author-email: Vorak <5m9mnf37q@mozmail.com>
License-File: LICENSE.txt
Keywords: Youtube,dlp,music
Classifier: Environment :: Console
Classifier: License :: OSI Approved :: MIT License
Classifier: Operating System :: Microsoft
Classifier: Operating System :: POSIX :: Linux
Classifier: Programming Language :: Python :: 3
Requires-Python: >=3.8
Requires-Dist: minute-count>=2025.4.39
Requires-Dist: mutagen>=1.40.0
Requires-Dist: pillow>=11.3.0
Requires-Dist: pycopy>=2025.7.48
Requires-Dist: requests>=2.20.0
Requires-Dist: yt-dlp>=2024.12.0
